{
  "config": {
    "num_outer": 3,
    "inner_cycles": 3,
    "pre_sweeps": 100,
    "group_size": 20,
    "r_reduced": 4,
    "exact_reference_enabled": false,
    "strict_compare": false,
    "sync_num_threads": 12,
    "basis_source": "message_conditioned_information"
  },
  "problem": {
    "num_poses": 512,
    "num_edges": 895
  },
  "initial_objective": 602585.04412994126,
  "direct_history": [
    {"outer": 0, "nonlinear_objective": 602585.04412994126, "linear_step_norm": 0, "linear_residual_norm": 0, "outer_total_sec": 0, "build_graph_sec": 0, "joint_assembly_sec": 0, "exact_solve_sec": 0, "apply_step_sec": 0, "objective_eval_sec": 0}
  ],
  "mg_history": [
    {"outer": 0, "nonlinear_objective": 602585.04412994126, "e_hat_norm": 0, "e_star_norm": 0, "e_rel_to_exact": 0, "linear_residual_exact": 0, "linear_residual_approx": 0, "num_groups": 0, "coarse_dim": 0, "outer_total_sec": 0, "build_graph_sec": 0, "basis_build_sec": 0, "coarse_lambda_sec": 0, "exact_joint_assembly_sec": 0, "exact_solve_sec": 0, "sweeps_sec": 0, "coarse_eta_sec": 0, "coarse_solve_sec": 0, "prolong_inject_sec": 0, "apply_step_sec": 0, "objective_eval_sec": 0},
    {"outer": 1, "nonlinear_objective": 70586.179494735596, "e_hat_norm": 2474.9634372943387, "e_star_norm": null, "e_rel_to_exact": null, "linear_residual_exact": null, "linear_residual_approx": null, "num_groups": 25, "coarse_dim": 100, "outer_total_sec": 0.046771300000000002, "build_graph_sec": 0.0042874999999999996, "basis_build_sec": 0.0065998000000000003, "coarse_lambda_sec": 0.0014005999999999999, "exact_joint_assembly_sec": 0, "exact_solve_sec": 0, "sweeps_sec": 0.0325627, "coarse_eta_sec": 0.00086380000000000007, "coarse_solve_sec": 0.00049890000000000004, "prolong_inject_sec": 0.00023720000000000002, "apply_step_sec": 4.8199999999999999e-05, "objective_eval_sec": 0.0002065},
    {"outer": 2, "nonlinear_objective": 1603.6040896074937, "e_hat_norm": 1257.4259319350203, "e_star_norm": null, "e_rel_to_exact": null, "linear_residual_exact": null, "linear_residual_approx": null, "num_groups": 25, "coarse_dim": 100, "outer_total_sec": 0.045192799999999998, "build_graph_sec": 0.0058466999999999998, "basis_build_sec": 0.0059147999999999996, "coarse_lambda_sec": 0.00055780000000000001, "exact_joint_assembly_sec": 0, "exact_solve_sec": 0, "sweeps_sec": 0.031279899999999999, "coarse_eta_sec": 0.00063729999999999993, "coarse_solve_sec": 0.00041219999999999999, "prolong_inject_sec": 0.0001917, "apply_step_sec": 5.7399999999999999e-05, "objective_eval_sec": 0.00024679999999999998},
    {"outer": 3, "nonlinear_objective": 620.19744553651526, "e_hat_norm": 280.32935020143805, "e_star_norm": null, "e_rel_to_exact": null, "linear_residual_exact": null, "linear_residual_approx": null, "num_groups": 25, "coarse_dim": 100, "outer_total_sec": 0.046511299999999998, "build_graph_sec": 0.0054669999999999996, "basis_build_sec": 0.0057765999999999998, "coarse_lambda_sec": 0.00055139999999999996, "exact_joint_assembly_sec": 0, "exact_solve_sec": 0, "sweeps_sec": 0.0326247, "coarse_eta_sec": 0.000776, "coarse_solve_sec": 0.00052900000000000006, "prolong_inject_sec": 0.00025119999999999998, "apply_step_sec": 8.2600000000000002e-05, "objective_eval_sec": 0.00038069999999999998}
  ]
}
